README.md
setup.py
src/logdogs.py
src/pyconfig.py
src/logdogs.egg-info/PKG-INFO
src/logdogs.egg-info/SOURCES.txt
src/logdogs.egg-info/dependency_links.txt
src/logdogs.egg-info/entry_points.txt
src/logdogs.egg-info/requires.txt
src/logdogs.egg-info/top_level.txt