Metadata-Version: 1.1
Name: logdogs
Version: 0.1.0
Summary: A daemon to monitor keywords in any log files specified by glob pattern
Home-page: https://github.com/yanxurui/logdog
Author: Xurui Yan
Author-email: yxr1993@gmail.com
License: MIT License
Keywords: log monitor
Platform: Linux
Classifier: Development Status :: 4 - Beta
Classifier: License :: OSI Approved :: MIT License
Classifier: Operating System :: Unix
Classifier: Programming Language :: Python :: 2.7
Classifier: Environment :: Console
Classifier: Topic :: Utilities
